{
  "_fv": 85,
  "_type": "procedure",
  "definition": {
    "procedurexml": "<xml xmlns=\"https://developers.google.com/blockly/xml\"><block type=\"event_trigger\" deletable=\"false\" x=\"0\" y=\"0\"><field name=\"trigger\">no_ext_trigger</field><next><block type=\"controls_if\"><value name=\"IF0\"><block type=\"blockstate_get_boolean_property\"><value name=\"property\"><block type=\"text\"><field name=\"TEXT\">waterlogged</field></block></value><value name=\"block\"><block type=\"blockstate_from_deps\"></block></value></block></value><statement name=\"DO0\"><block type=\"java_code\"><field name=\"CODE\">&amp;#10;//КОСТЫЛЬ, НЕ УБИРАТЬ, ЕСЛИ ИСПОЛЬЗУЕТЕ MCreator. НА НЁМ ДЕРЖИТСЯ ПРОЦЕДУРА</field><next><block type=\"block_set_boolean_property\"><value name=\"property\"><block type=\"text\"><field name=\"TEXT\">KosTil</field></block></value><value name=\"x\"><block type=\"coord_x\"></block></value><value name=\"y\"><block type=\"coord_y\"></block></value><value name=\"z\"><block type=\"coord_z\"></block></value><value name=\"value\"><block type=\"logic_boolean\"><field name=\"BOOL\">TRUE</field></block></value></block></next></block></statement><next><block type=\"java_code\"><field name=\"CODE\">&amp;#10;        // Константы свойств блока&amp;#10;        final String PROP_BLOCKSTATE = \"blockstate\";&amp;#10;        final String PROP_BOLTED = \"bolted\";&amp;#10;        final String PROP_EMERGENCY = \"emergency_acs\";&amp;#10;        final String PROP_PANEL = \"panel_open\";&amp;#10;        final int[] ANIM_CLOSE = {4, 3, 2, 1, 0};&amp;#10;&amp;#10;        BlockPos pos = BlockPos.containing(x, y, z);&amp;#10;        BlockPos topPos = pos.above();&amp;#10;&amp;#10;        // 🔧 ИСПРАВЛЕНИЕ #1: Инициализация NBT ДО проверки логики шлюза!&amp;#10;        // Чтобы timer/safe и другие флаги были доступны при планировании закрытия&amp;#10;        initializeBlockNBT(world, pos);&amp;#10;&amp;#10;        // Создаём верхний блок-плагин, если его нет&amp;#10;        ensureTopBlockExists(world, topPos, blockstate);&amp;#10;&amp;#10;        // Основная логика: закрытый шлюз → инициализация, открытый → планирование закрытия&amp;#10;        if (isClosedAirlock(world, pos)) {&amp;#10;            initializeClosedAirlockState(world, pos, blockstate, PROP_BLOCKSTATE, PROP_BOLTED, PROP_EMERGENCY, PROP_PANEL);&amp;#10;        } else if (isOpenAirlock(world, pos)) {&amp;#10;            scheduleAutoCloseLogic(world, pos, blockstate, PROP_BOLTED);&amp;#10;        }&amp;#10;&amp;#10;        // 🔧 ИСПРАВЛЕНИЕ #2: Рандомизация кабелей ПОСЛЕ инициализации NBT&amp;#10;        // Используем позицию блока как часть сида для уникального рандома на каждый шлюз&amp;#10;        generateRandomCableValues(world, pos);&amp;#10;    }&amp;#10;&amp;#10;    // ============================================================================&amp;#10;    // 🏷️ МОДУЛЬ 2: ПРОВЕРКА ТЕГОВ (OPEN/CLOSED)&amp;#10;    // Неймспейс тегов: ssc14 (без подчёркивания) — как в MCreator&amp;#10;    // ============================================================================&amp;#10;    private static boolean isClosedAirlock(LevelAccessor world, BlockPos pos) {&amp;#10;        return world.getBlockState(pos).is(BlockTags.create(ResourceLocation.parse(\"ssc14:airlocks_closed\")));&amp;#10;    }&amp;#10;&amp;#10;    private static boolean isOpenAirlock(LevelAccessor world, BlockPos pos) {&amp;#10;        return world.getBlockState(pos).is(BlockTags.create(ResourceLocation.parse(\"ssc14:airlocks_open\")));&amp;#10;    }&amp;#10;&amp;#10;    // ============================================================================&amp;#10;    // 🧱 МОДУЛЬ 3: УПРАВЛЕНИЕ БЛОКАМИ (PLUG / MATCHING)&amp;#10;    // Неймспейс блоков: ssc_14 (с подчёркиванием!) — как в реестре&amp;#10;    // ============================================================================&amp;#10;    private static void ensureTopBlockExists(LevelAccessor world, BlockPos topPos, BlockState sourceState) {&amp;#10;        if (isAirlockPlug(world.getBlockState(topPos))) return;&amp;#10;        BlockState newTop = createMatchingPlugBlock(sourceState, false);&amp;#10;        newTop = copyBlockProperties(sourceState, newTop);&amp;#10;        world.setBlock(topPos, newTop, 3);&amp;#10;    }&amp;#10;&amp;#10;    private static boolean isAirlockPlug(BlockState state) {&amp;#10;        return BuiltInRegistries.BLOCK.getKey(state.getBlock()).getPath().contains(\"airlock_up_plug\");&amp;#10;    }&amp;#10;&amp;#10;    private static BlockState createMatchingPlugBlock(BlockState sourceState, boolean open) {&amp;#10;        String sourceName = BuiltInRegistries.BLOCK.getKey(sourceState.getBlock()).getPath();&amp;#10;        String prefix = sourceName.replaceAll(\"_airlock_d_\\\\d+.*$\", \"\");&amp;#10;        String plugName = prefix + \"_airlock_up_plug\" + (open ? \"open\" : \"\");&amp;#10;        Block plugBlock = BuiltInRegistries.BLOCK.getOptional(ResourceLocation.tryParse(\"ssc_14:\" + plugName))&amp;#10;            .orElse(open ? Ssc14ModBlocks.AIRLOCK_UP_PLUG_OPEN.get() : Ssc14ModBlocks.AIRLOCK_UP_PLUG.get());&amp;#10;        return plugBlock.defaultBlockState();&amp;#10;    }&amp;#10;&amp;#10;    // ============================================================================&amp;#10;    // ⚙️ МОДУЛЬ 4: ИНИЦИАЛИЗАЦИЯ СОСТОЯНИЯ ЗАКРЫТОГО ШЛЮЗА&amp;#10;    // Устанавливает blockstate на основе флагов: bolted, emergency, panelOpen&amp;#10;    // ============================================================================&amp;#10;    private record AirlockFlags(boolean bolted, boolean emergency, boolean panelOpen) {&amp;#10;        static AirlockFlags of(boolean b, boolean e, boolean p) { return new AirlockFlags(b, e, p); }&amp;#10;    }&amp;#10;&amp;#10;    private static void initializeClosedAirlockState(LevelAccessor world, BlockPos pos, BlockState state, String propBlockstate, String propBolted, String propEmergency, String propPanel) {&amp;#10;        IntegerProperty stateProp = getStateProperty(state, propBlockstate);&amp;#10;        if (stateProp == null) return;&amp;#10;        int currentState = state.getValue(stateProp);&amp;#10;        if (currentState &gt;= 1 &amp;&amp; currentState &lt;= 4) return; // Уже в анимации&amp;#10;&amp;#10;        boolean bolted = getBooleanProperty(state, propBolted, false);&amp;#10;        boolean emergency = getBooleanProperty(state, propEmergency, false);&amp;#10;        boolean panelOpen = getBooleanProperty(state, propPanel, false);&amp;#10;        boolean diodsEnabled = getBlockNBT(world, pos, \"diods\");&amp;#10;&amp;#10;        int newValue = switch (AirlockFlags.of(bolted, emergency, panelOpen)) {&amp;#10;            case AirlockFlags f when f.bolted() &amp;&amp; f.panelOpen() -&gt; 9;&amp;#10;            case AirlockFlags f when f.bolted() &amp;&amp; !f.panelOpen() -&gt; diodsEnabled ? 5 : 0;&amp;#10;            case AirlockFlags f when !f.bolted() &amp;&amp; f.emergency() &amp;&amp; f.panelOpen() -&gt; 8;&amp;#10;            case AirlockFlags f when !f.bolted() &amp;&amp; f.emergency() &amp;&amp; !f.panelOpen() -&gt; diodsEnabled ? 6 : 0;&amp;#10;            case AirlockFlags f when !f.bolted() &amp;&amp; !f.emergency() &amp;&amp; f.panelOpen() -&gt; 7;&amp;#10;            default -&gt; 0;&amp;#10;        };&amp;#10;        setBlockStateValue(world, pos, stateProp, newValue);&amp;#10;    }&amp;#10;&amp;#10;    // ============================================================================&amp;#10;    // ⏱️ МОДУЛЬ 5: ЛОГИКА АВТО-ЗАКРЫТИЯ (ТАЙМЕР)&amp;#10;    // 🔧 ИСПРАВЛЕНИЕ: таймер теперь работает корректно (80т если true, 10т если false)&amp;#10;    // ============================================================================&amp;#10;    private static void scheduleAutoCloseLogic(LevelAccessor world, BlockPos pos, BlockState state, String propBolted) {&amp;#10;        if (!(world instanceof Level level) || level.isClientSide()) return;&amp;#10;        if (getBooleanProperty(state, propBolted, false)) return; // Заблокирован болтом&amp;#10;&amp;#10;        // 🔧 Читаем флаг таймера из NBT (теперь доступен, т.к. initializeBlockNBT вызван раньше)&amp;#10;        boolean timerEnabled = getBlockNBT(world, pos, \"timer\");&amp;#10;        int delay = timerEnabled ? 80 : 10; // 80 тиков = 4 секунды, 10 тиков = 0.5 секунды&amp;#10;&amp;#10;        Ssc14Mod.queueServerWork(delay, () -&gt; tryCloseAirlock(world, pos, propBolted));&amp;#10;    }&amp;#10;&amp;#10;    private static void tryCloseAirlock(LevelAccessor world, BlockPos pos, String propBolted) {&amp;#10;        if (!(world instanceof Level level) || level.isClientSide()) return;&amp;#10;        if (!isOpenAirlock(world, pos)) return; // Уже не открыт&amp;#10;        if (getBooleanProperty(world.getBlockState(pos), propBolted, false)) return; // Заблокировали&amp;#10;&amp;#10;        boolean safeMode = getBlockNBT(world, pos, \"safe\");&amp;#10;        boolean hasEntities = hasEntitiesInAirlock(world, pos);&amp;#10;&amp;#10;        if (hasEntities) {&amp;#10;            if (safeMode) {&amp;#10;                // Повторная попытка через 1 секунду (20 тиков)&amp;#10;                Ssc14Mod.queueServerWork(20, () -&gt; tryCloseAirlock(world, pos, propBolted));&amp;#10;                return;&amp;#10;            } else {&amp;#10;                // Опасный режим: наносим урон сущностям&amp;#10;                damageEntitiesInAirlock(world, pos, 10.0f);&amp;#10;            }&amp;#10;        }&amp;#10;        performAirlockClose(world, pos);&amp;#10;    }&amp;#10;&amp;#10;    // ============================================================================&amp;#10;    // 👥 МОДУЛЬ 6: ПРОВЕРКА СУЩНОСТЕЙ В ШЛЮЗЕ&amp;#10;    // ============================================================================&amp;#10;    private static boolean hasEntitiesInAirlock(LevelAccessor world, BlockPos pos) {&amp;#10;        double r = 0.2;&amp;#10;        return !world.getEntitiesOfClass(Entity.class,&amp;#10;            new AABB(pos.getX()-r, pos.getY()-r, pos.getZ()-r, pos.getX()+1+r, pos.getY()+1+r, pos.getZ()+1+r),&amp;#10;            e -&gt; e instanceof Player || e instanceof Mob).isEmpty();&amp;#10;    }&amp;#10;&amp;#10;    private static void damageEntitiesInAirlock(LevelAccessor world, BlockPos pos, float damageAmount) {&amp;#10;        if (!(world instanceof Level level)) return;&amp;#10;        AABB box = new AABB(pos.getX()-0.2, pos.getY()-0.2, pos.getZ()-0.2, pos.getX()+1.2, pos.getY()+1.2, pos.getZ()+1.2);&amp;#10;        for (Entity e : world.getEntitiesOfClass(Entity.class, box, ent -&gt; ent instanceof Player || ent instanceof Mob)) {&amp;#10;            if (e != null) e.hurt(level.damageSources().generic(), damageAmount);&amp;#10;        }&amp;#10;    }&amp;#10;&amp;#10;    // ============================================================================&amp;#10;    // 🎬 МОДУЛЬ 7: АНИМАЦИЯ ЗАКРЫТИЯ ШЛЮЗА&amp;#10;    // 🔊 Звук + замена блока + анимация blockstate: 4→3→2→1→0&amp;#10;    // ============================================================================&amp;#10;    private static void performAirlockClose(LevelAccessor world, BlockPos pos) {&amp;#10;        if (!(world instanceof Level level)) return;&amp;#10;&amp;#10;        // Проигрываем звук закрытия (неймспейс ssc_14 с подчёркиванием)&amp;#10;        BuiltInRegistries.SOUND_EVENT.getOptional(ResourceLocation.parse(\"ssc_14:airlock_close\"))&amp;#10;            .ifPresent(sound -&gt; level.playSound(null, pos, sound, SoundSource.NEUTRAL, 1f, 1f));&amp;#10;&amp;#10;        // Заменяем блок на закрытую версию + переносим NBT&amp;#10;        replaceBlockWithNBT(world, pos);&amp;#10;&amp;#10;        // Получаем свойство blockstate у нового (закрытого) блока&amp;#10;        BlockState afterReplace = world.getBlockState(pos);&amp;#10;        Property&lt;?&gt; rawProp = afterReplace.getBlock().getStateDefinition().getProperty(\"blockstate\");&amp;#10;        IntegerProperty stateProp = (rawProp instanceof IntegerProperty) ? (IntegerProperty) rawProp : null;&amp;#10;&amp;#10;        if (stateProp == null) return;&amp;#10;&amp;#10;        // Устанавливаем стартовое значение анимации = 4&amp;#10;        if (stateProp.getPossibleValues().contains(4)) {&amp;#10;            world.setBlock(pos, afterReplace.setValue(stateProp, 4), 3);&amp;#10;        }&amp;#10;&amp;#10;        // Запускаем анимацию 4→3→2→1→0&amp;#10;        runBlockAnimation(world, pos, new int[]{4, 3, 2, 1, 0}, stateProp);&amp;#10;    }&amp;#10;&amp;#10;    private static void replaceBlockWithNBT(LevelAccessor world, BlockPos pos) {&amp;#10;        BlockPos topPos = pos.above();&amp;#10;        CompoundTag savedData = null;&amp;#10;        BlockEntity be = world.getBlockEntity(pos);&amp;#10;        if (be != null) { savedData = be.getPersistentData().copy(); be.setRemoved(); }&amp;#10;&amp;#10;        BlockState oldMain = world.getBlockState(pos);&amp;#10;        BlockState newMain = findMatchingBlock(oldMain, true); // true = закрытая версия&amp;#10;        BlockState finalMain = copyBlockProperties(oldMain, newMain);&amp;#10;        world.setBlock(pos, finalMain, 3);&amp;#10;&amp;#10;        if (savedData != null) {&amp;#10;            BlockEntity newBe = world.getBlockEntity(pos);&amp;#10;            if (newBe != null) newBe.getPersistentData().merge(savedData);&amp;#10;        }&amp;#10;&amp;#10;        BlockState oldTop = world.getBlockState(topPos);&amp;#10;        BlockState newTop = findMatchingPlugBlock(oldTop, true);&amp;#10;        BlockState finalTop = copyBlockProperties(oldTop, newTop);&amp;#10;        world.setBlock(topPos, finalTop, 3);&amp;#10;    }&amp;#10;&amp;#10;    // 🔧 Универсальный поиск пары блока: закрытый = без суффикса, открытый = +open&amp;#10;    private static BlockState findMatchingBlock(BlockState currentState, boolean toClosed) {&amp;#10;        String currentName = BuiltInRegistries.BLOCK.getKey(currentState.getBlock()).getPath();&amp;#10;        String baseName = currentName.endsWith(\"open\") ? currentName.substring(0, currentName.length() - 4) : currentName;&amp;#10;        String newName = toClosed ? baseName : baseName + \"open\";&amp;#10;&amp;#10;        // 🔧 Неймспейс ssc_14: для блоков (с подчёркиванием!)&amp;#10;        Block newBlock = BuiltInRegistries.BLOCK.getOptional(ResourceLocation.tryParse(\"ssc_14:\" + newName))&amp;#10;            .orElse(currentState.getBlock());&amp;#10;        return newBlock.defaultBlockState();&amp;#10;    }&amp;#10;&amp;#10;    private static BlockState findMatchingPlugBlock(BlockState currentState, boolean toClosed) {&amp;#10;        String currentName = BuiltInRegistries.BLOCK.getKey(currentState.getBlock()).getPath();&amp;#10;        String baseName = currentName.endsWith(\"open\") ? currentName.substring(0, currentName.length() - 4) : currentName;&amp;#10;        String newName = toClosed ? baseName : baseName + \"open\";&amp;#10;&amp;#10;        Block newBlock = BuiltInRegistries.BLOCK.getOptional(ResourceLocation.tryParse(\"ssc_14:\" + newName))&amp;#10;            .orElse(currentState.getBlock());&amp;#10;        return newBlock.defaultBlockState();&amp;#10;    }&amp;#10;&amp;#10;    // ============================================================================&amp;#10;    // 🎞️ МОДУЛЬ 8: ПОШАГОВАЯ АНИМАЦИЯ BLOCKSTATE&amp;#10;    // ============================================================================&amp;#10;    private static void runBlockAnimation(LevelAccessor world, BlockPos pos, int[] states, IntegerProperty prop) {&amp;#10;        if (prop == null || states.length == 0) return;&amp;#10;        runAnimationStep(world, pos, prop, states, 0);&amp;#10;    }&amp;#10;&amp;#10;    private static void runAnimationStep(LevelAccessor world, BlockPos pos, IntegerProperty prop, int[] states, int index) {&amp;#10;        if (index &gt;= states.length) return;&amp;#10;        BlockState current = world.getBlockState(pos);&amp;#10;        int target = states[index];&amp;#10;&amp;#10;        if (prop.getPossibleValues().contains(target)) {&amp;#10;            world.setBlock(pos, current.setValue(prop, target), 3);&amp;#10;        }&amp;#10;&amp;#10;        if (index + 1 &lt; states.length) {&amp;#10;            Ssc14Mod.queueServerWork(2, () -&gt; runAnimationStep(world, pos, prop, states, index + 1));&amp;#10;        }&amp;#10;    }&amp;#10;&amp;#10;    // ============================================================================&amp;#10;    // 💾 МОДУЛЬ 9: ИНИЦИАЛИЗАЦИЯ И РАНДОМИЗАЦИЯ NBT&amp;#10;    // 🔧 ИСПРАВЛЕНИЕ: рандомизация кабелей теперь уникальна для каждого шлюза&amp;#10;    // ============================================================================&amp;#10;    private static void initializeBlockNBT(LevelAccessor world, BlockPos pos) {&amp;#10;        if (world.isClientSide()) return;&amp;#10;        BlockEntity be = world.getBlockEntity(pos);&amp;#10;        if (be == null || be.getPersistentData().getBooleanOr(\"Blocking_13\", false)) return;&amp;#10;&amp;#10;        CompoundTag nbt = be.getPersistentData();&amp;#10;        nbt.putBoolean(\"Blocking_13\", true); // Флаг \"уже инициализирован\"&amp;#10;&amp;#10;        // Дефолтные значения функций шлюза&amp;#10;        nbt.putBoolean(\"energy_cabel_1\", true);&amp;#10;        nbt.putBoolean(\"energy_cabel_2\", true);&amp;#10;        nbt.putBoolean(\"timer\", true);        // 🔧 По умолчанию таймер ВКЛЮЧЕН (80 тиков)&amp;#10;        nbt.putBoolean(\"ai_access\", true);&amp;#10;        nbt.putBoolean(\"logs\", true);&amp;#10;        nbt.putBoolean(\"diods\", true);&amp;#10;        nbt.putBoolean(\"safe\", true);&amp;#10;    }&amp;#10;&amp;#10;    private static void generateRandomCableValues(LevelAccessor world, BlockPos pos) {&amp;#10;        if (world.isClientSide()) return;&amp;#10;        BlockEntity be = world.getBlockEntity(pos);&amp;#10;        if (be == null || be.getPersistentData().getBooleanOr(\"random_cab\", false)) return;&amp;#10;&amp;#10;        CompoundTag nbt = be.getPersistentData();&amp;#10;        nbt.putBoolean(\"random_cab\", true); // Флаг \"уже рандомизирован\"&amp;#10;&amp;#10;        // 🔧 ИСПРАВЛЕНИЕ: Уникальный сид для каждого шлюза на основе его координат!&amp;#10;        // Используем XOR координат с world seed для детерминированного, но уникального рандома&amp;#10;        long uniqueSeed = world.getRandom().nextLong() ^ ((long)pos.getX() &lt;&lt; 24) ^ ((long)pos.getZ() &lt;&lt; 8) ^ pos.getY();&amp;#10;        Random rand = new Random(uniqueSeed);&amp;#10;&amp;#10;        List&lt;Integer&gt; values = new ArrayList&lt;&gt;(Arrays.asList(0, 1, 2, 3, 4, 5, 6, 7));&amp;#10;        Collections.shuffle(values, rand); // Перемешиваем значения 0-7&amp;#10;&amp;#10;        // Присваиваем каждому кабелю (log_cab_1...8) уникальное значение без повторов&amp;#10;        for (int i = 0; i &lt; 8; i++) {&amp;#10;            nbt.putInt(\"log_cab_\" + (i + 1), values.get(i));&amp;#10;        }&amp;#10;    }&amp;#10;&amp;#10;    // ============================================================================&amp;#10;    // 🧰 МОДУЛЬ 10: ВСПОМОГАТЕЛЬНЫЕ МЕТОДЫ (UTILS)&amp;#10;    // ============================================================================&amp;#10;    private static BlockState copyBlockProperties(BlockState from, BlockState to) {&amp;#10;        BlockState result = to;&amp;#10;        for (Property&lt;?&gt; oldProp : from.getProperties()) {&amp;#10;            Property&lt;?&gt; newProp = result.getBlock().getStateDefinition().getProperty(oldProp.getName());&amp;#10;            if (newProp != null &amp;&amp; newProp.getValueClass().isAssignableFrom(oldProp.getValueClass())) {&amp;#10;                try {&amp;#10;                    @SuppressWarnings({\"rawtypes\",\"unchecked\"}) Property rawProp = newProp;&amp;#10;                    @SuppressWarnings({\"rawtypes\",\"unchecked\"}) Comparable value = (Comparable) from.getValue(oldProp);&amp;#10;                    result = result.setValue(rawProp, value);&amp;#10;                } catch (Exception ignored) {}&amp;#10;            }&amp;#10;        }&amp;#10;        return result;&amp;#10;    }&amp;#10;&amp;#10;    private static IntegerProperty getStateProperty(BlockState state, String propName) {&amp;#10;        Property&lt;?&gt; prop = state.getBlock().getStateDefinition().getProperty(propName);&amp;#10;        return (prop instanceof IntegerProperty ip &amp;&amp; ip.getPossibleValues().contains(0)) ? ip : null;&amp;#10;    }&amp;#10;&amp;#10;    private static boolean getBooleanProperty(BlockState state, String propName, boolean defaultValue) {&amp;#10;        Property&lt;?&gt; prop = state.getBlock().getStateDefinition().getProperty(propName);&amp;#10;        return (prop instanceof BooleanProperty bp) ? state.getValue(bp) : defaultValue;&amp;#10;    }&amp;#10;&amp;#10;    private static boolean getBlockNBT(LevelAccessor world, BlockPos pos, String tag) {&amp;#10;        BlockEntity be = world.getBlockEntity(pos);&amp;#10;        return be != null &amp;&amp; be.getPersistentData().getBooleanOr(tag, false);&amp;#10;    }&amp;#10;&amp;#10;    private static void setBlockStateValue(LevelAccessor world, BlockPos pos, IntegerProperty prop, int value) {&amp;#10;        if (prop != null &amp;&amp; prop.getPossibleValues().contains(value)) {&amp;#10;            BlockState current = world.getBlockState(pos);&amp;#10;            world.setBlock(pos, current.setValue(prop, value), 3);&amp;#10;        }</field></block></next></block></next></block></xml>",
    "skipDependencyNullCheck": false
  }
}